{"id":8797753,"name":"changes","full_name":"indexzero/changes","owner":{"login":"indexzero","id":4624,"avatar_url":"https://avatars.githubusercontent.com/u/4624?v=3","gravatar_id":"","url":"https://api.github.com/users/indexzero","html_url":"https://github.com/indexzero","followers_url":"https://api.github.com/users/indexzero/followers","following_url":"https://api.github.com/users/indexzero/following{/other_user}","gists_url":"https://api.github.com/users/indexzero/gists{/gist_id}","starred_url":"https://api.github.com/users/indexzero/starred{/owner}{/repo}","subscriptions_url":"https://api.github.com/users/indexzero/subscriptions","organizations_url":"https://api.github.com/users/indexzero/orgs","repos_url":"https://api.github.com/users/indexzero/repos","events_url":"https://api.github.com/users/indexzero/events{/privacy}","received_events_url":"https://api.github.com/users/indexzero/received_events","type":"User","site_admin":false},"private":false,"html_url":"https://github.com/indexzero/changes","description":"A consistent, fault tolerant CouchDB _changes listener with pre-fetch support","fork":false,"url":"https://api.github.com/repos/indexzero/changes","forks_url":"https://api.github.com/repos/indexzero/changes/forks","keys_url":"https://api.github.com/repos/indexzero/changes/keys{/key_id}","collaborators_url":"https://api.github.com/repos/indexzero/changes/collaborators{/collaborator}","teams_url":"https://api.github.com/repos/indexzero/changes/teams","hooks_url":"https://api.github.com/repos/indexzero/changes/hooks","issue_events_url":"https://api.github.com/repos/indexzero/changes/issues/events{/number}","events_url":"https://api.github.com/repos/indexzero/changes/events","assignees_url":"https://api.github.com/repos/indexzero/changes/assignees{/user}","branches_url":"https://api.github.com/repos/indexzero/changes/branches{/branch}","tags_url":"https://api.github.com/repos/indexzero/changes/tags","blobs_url":"https://api.github.com/repos/indexzero/changes/git/blobs{/sha}","git_tags_url":"https://api.github.com/repos/indexzero/changes/git/tags{/sha}","git_refs_url":"https://api.github.com/repos/indexzero/changes/git/refs{/sha}","trees_url":"https://api.github.com/repos/indexzero/changes/git/trees{/sha}","statuses_url":"https://api.github.com/repos/indexzero/changes/statuses/{sha}","languages_url":"https://api.github.com/repos/indexzero/changes/languages","stargazers_url":"https://api.github.com/repos/indexzero/changes/stargazers","contributors_url":"https://api.github.com/repos/indexzero/changes/contributors","subscribers_url":"https://api.github.com/repos/indexzero/changes/subscribers","subscription_url":"https://api.github.com/repos/indexzero/changes/subscription","commits_url":"https://api.github.com/repos/indexzero/changes/commits{/sha}","git_commits_url":"https://api.github.com/repos/indexzero/changes/git/commits{/sha}","comments_url":"https://api.github.com/repos/indexzero/changes/comments{/number}","issue_comment_url":"https://api.github.com/repos/indexzero/changes/issues/comments{/number}","contents_url":"https://api.github.com/repos/indexzero/changes/contents/{+path}","compare_url":"https://api.github.com/repos/indexzero/changes/compare/{base}...{head}","merges_url":"https://api.github.com/repos/indexzero/changes/merges","archive_url":"https://api.github.com/repos/indexzero/changes/{archive_format}{/ref}","downloads_url":"https://api.github.com/repos/indexzero/changes/downloads","issues_url":"https://api.github.com/repos/indexzero/changes/issues{/number}","pulls_url":"https://api.github.com/repos/indexzero/changes/pulls{/number}","milestones_url":"https://api.github.com/repos/indexzero/changes/milestones{/number}","notifications_url":"https://api.github.com/repos/indexzero/changes/notifications{?since,all,participating}","labels_url":"https://api.github.com/repos/indexzero/changes/labels{/name}","releases_url":"https://api.github.com/repos/indexzero/changes/releases{/id}","deployments_url":"https://api.github.com/repos/indexzero/changes/deployments","created_at":"2013-03-15T11:34:23Z","updated_at":"2014-08-14T00:58:50Z","pushed_at":"2014-08-14T00:58:49Z","git_url":"git://github.com/indexzero/changes.git","ssh_url":"git@github.com:indexzero/changes.git","clone_url":"https://github.com/indexzero/changes.git","svn_url":"https://github.com/indexzero/changes","homepage":null,"size":167,"stargazers_count":9,"watchers_count":9,"language":"JavaScript","has_issues":true,"has_downloads":true,"has_wiki":true,"has_pages":false,"forks_count":2,"mirror_url":null,"open_issues_count":1,"forks":2,"open_issues":1,"watchers":9,"default_branch":"master","permissions":{"admin":false,"push":false,"pull":true},"network_count":2,"subscribers_count":3}