{"id":19867319,"name":"pivotal-ui","full_name":"pivotal-cf/pivotal-ui","owner":{"login":"pivotal-cf","id":5497370,"avatar_url":"https://avatars.githubusercontent.com/u/5497370?v=3","gravatar_id":"","url":"https://api.github.com/users/pivotal-cf","html_url":"https://github.com/pivotal-cf","followers_url":"https://api.github.com/users/pivotal-cf/followers","following_url":"https://api.github.com/users/pivotal-cf/following{/other_user}","gists_url":"https://api.github.com/users/pivotal-cf/gists{/gist_id}","starred_url":"https://api.github.com/users/pivotal-cf/starred{/owner}{/repo}","subscriptions_url":"https://api.github.com/users/pivotal-cf/subscriptions","organizations_url":"https://api.github.com/users/pivotal-cf/orgs","repos_url":"https://api.github.com/users/pivotal-cf/repos","events_url":"https://api.github.com/users/pivotal-cf/events{/privacy}","received_events_url":"https://api.github.com/users/pivotal-cf/received_events","type":"Organization","site_admin":false},"private":false,"html_url":"https://github.com/pivotal-cf/pivotal-ui","description":"","fork":false,"url":"https://api.github.com/repos/pivotal-cf/pivotal-ui","forks_url":"https://api.github.com/repos/pivotal-cf/pivotal-ui/forks","keys_url":"https://api.github.com/repos/pivotal-cf/pivotal-ui/keys{/key_id}","collaborators_url":"https://api.github.com/repos/pivotal-cf/pivotal-ui/collaborators{/collaborator}","teams_url":"https://api.github.com/repos/pivotal-cf/pivotal-ui/teams","hooks_url":"https://api.github.com/repos/pivotal-cf/pivotal-ui/hooks","issue_events_url":"https://api.github.com/repos/pivotal-cf/pivotal-ui/issues/events{/number}","events_url":"https://api.github.com/repos/pivotal-cf/pivotal-ui/events","assignees_url":"https://api.github.com/repos/pivotal-cf/pivotal-ui/assignees{/user}","branches_url":"https://api.github.com/repos/pivotal-cf/pivotal-ui/branches{/branch}","tags_url":"https://api.github.com/repos/pivotal-cf/pivotal-ui/tags","blobs_url":"https://api.github.com/repos/pivotal-cf/pivotal-ui/git/blobs{/sha}","git_tags_url":"https://api.github.com/repos/pivotal-cf/pivotal-ui/git/tags{/sha}","git_refs_url":"https://api.github.com/repos/pivotal-cf/pivotal-ui/git/refs{/sha}","trees_url":"https://api.github.com/repos/pivotal-cf/pivotal-ui/git/trees{/sha}","statuses_url":"https://api.github.com/repos/pivotal-cf/pivotal-ui/statuses/{sha}","languages_url":"https://api.github.com/repos/pivotal-cf/pivotal-ui/languages","stargazers_url":"https://api.github.com/repos/pivotal-cf/pivotal-ui/stargazers","contributors_url":"https://api.github.com/repos/pivotal-cf/pivotal-ui/contributors","subscribers_url":"https://api.github.com/repos/pivotal-cf/pivotal-ui/subscribers","subscription_url":"https://api.github.com/repos/pivotal-cf/pivotal-ui/subscription","commits_url":"https://api.github.com/repos/pivotal-cf/pivotal-ui/commits{/sha}","git_commits_url":"https://api.github.com/repos/pivotal-cf/pivotal-ui/git/commits{/sha}","comments_url":"https://api.github.com/repos/pivotal-cf/pivotal-ui/comments{/number}","issue_comment_url":"https://api.github.com/repos/pivotal-cf/pivotal-ui/issues/comments{/number}","contents_url":"https://api.github.com/repos/pivotal-cf/pivotal-ui/contents/{+path}","compare_url":"https://api.github.com/repos/pivotal-cf/pivotal-ui/compare/{base}...{head}","merges_url":"https://api.github.com/repos/pivotal-cf/pivotal-ui/merges","archive_url":"https://api.github.com/repos/pivotal-cf/pivotal-ui/{archive_format}{/ref}","downloads_url":"https://api.github.com/repos/pivotal-cf/pivotal-ui/downloads","issues_url":"https://api.github.com/repos/pivotal-cf/pivotal-ui/issues{/number}","pulls_url":"https://api.github.com/repos/pivotal-cf/pivotal-ui/pulls{/number}","milestones_url":"https://api.github.com/repos/pivotal-cf/pivotal-ui/milestones{/number}","notifications_url":"https://api.github.com/repos/pivotal-cf/pivotal-ui/notifications{?since,all,participating}","labels_url":"https://api.github.com/repos/pivotal-cf/pivotal-ui/labels{/name}","releases_url":"https://api.github.com/repos/pivotal-cf/pivotal-ui/releases{/id}","deployments_url":"https://api.github.com/repos/pivotal-cf/pivotal-ui/deployments","created_at":"2014-05-16T18:52:56Z","updated_at":"2016-07-12T11:49:48Z","pushed_at":"2016-06-29T15:46:08Z","git_url":"git://github.com/pivotal-cf/pivotal-ui.git","ssh_url":"git@github.com:pivotal-cf/pivotal-ui.git","clone_url":"https://github.com/pivotal-cf/pivotal-ui.git","svn_url":"https://github.com/pivotal-cf/pivotal-ui","homepage":"styleguide.cfapps.io","size":41625,"stargazers_count":256,"watchers_count":256,"language":"JavaScript","has_issues":true,"has_downloads":true,"has_wiki":true,"has_pages":false,"forks_count":35,"mirror_url":null,"open_issues_count":17,"forks":35,"open_issues":17,"watchers":256,"default_branch":"development","permissions":{"admin":false,"push":false,"pull":true},"organization":{"login":"pivotal-cf","id":5497370,"avatar_url":"https://avatars.githubusercontent.com/u/5497370?v=3","gravatar_id":"","url":"https://api.github.com/users/pivotal-cf","html_url":"https://github.com/pivotal-cf","followers_url":"https://api.github.com/users/pivotal-cf/followers","following_url":"https://api.github.com/users/pivotal-cf/following{/other_user}","gists_url":"https://api.github.com/users/pivotal-cf/gists{/gist_id}","starred_url":"https://api.github.com/users/pivotal-cf/starred{/owner}{/repo}","subscriptions_url":"https://api.github.com/users/pivotal-cf/subscriptions","organizations_url":"https://api.github.com/users/pivotal-cf/orgs","repos_url":"https://api.github.com/users/pivotal-cf/repos","events_url":"https://api.github.com/users/pivotal-cf/events{/privacy}","received_events_url":"https://api.github.com/users/pivotal-cf/received_events","type":"Organization","site_admin":false},"network_count":35,"subscribers_count":136}