{"id":46228418,"name":"houdin","full_name":"ruiquelhas/houdin","owner":{"login":"ruiquelhas","id":413255,"avatar_url":"https://avatars.githubusercontent.com/u/413255?v=3","gravatar_id":"","url":"https://api.github.com/users/ruiquelhas","html_url":"https://github.com/ruiquelhas","followers_url":"https://api.github.com/users/ruiquelhas/followers","following_url":"https://api.github.com/users/ruiquelhas/following{/other_user}","gists_url":"https://api.github.com/users/ruiquelhas/gists{/gist_id}","starred_url":"https://api.github.com/users/ruiquelhas/starred{/owner}{/repo}","subscriptions_url":"https://api.github.com/users/ruiquelhas/subscriptions","organizations_url":"https://api.github.com/users/ruiquelhas/orgs","repos_url":"https://api.github.com/users/ruiquelhas/repos","events_url":"https://api.github.com/users/ruiquelhas/events{/privacy}","received_events_url":"https://api.github.com/users/ruiquelhas/received_events","type":"User","site_admin":false},"private":false,"html_url":"https://github.com/ruiquelhas/houdin","description":"Route-level file type validation for hapi parsed in-memory request payloads","fork":false,"url":"https://api.github.com/repos/ruiquelhas/houdin","forks_url":"https://api.github.com/repos/ruiquelhas/houdin/forks","keys_url":"https://api.github.com/repos/ruiquelhas/houdin/keys{/key_id}","collaborators_url":"https://api.github.com/repos/ruiquelhas/houdin/collaborators{/collaborator}","teams_url":"https://api.github.com/repos/ruiquelhas/houdin/teams","hooks_url":"https://api.github.com/repos/ruiquelhas/houdin/hooks","issue_events_url":"https://api.github.com/repos/ruiquelhas/houdin/issues/events{/number}","events_url":"https://api.github.com/repos/ruiquelhas/houdin/events","assignees_url":"https://api.github.com/repos/ruiquelhas/houdin/assignees{/user}","branches_url":"https://api.github.com/repos/ruiquelhas/houdin/branches{/branch}","tags_url":"https://api.github.com/repos/ruiquelhas/houdin/tags","blobs_url":"https://api.github.com/repos/ruiquelhas/houdin/git/blobs{/sha}","git_tags_url":"https://api.github.com/repos/ruiquelhas/houdin/git/tags{/sha}","git_refs_url":"https://api.github.com/repos/ruiquelhas/houdin/git/refs{/sha}","trees_url":"https://api.github.com/repos/ruiquelhas/houdin/git/trees{/sha}","statuses_url":"https://api.github.com/repos/ruiquelhas/houdin/statuses/{sha}","languages_url":"https://api.github.com/repos/ruiquelhas/houdin/languages","stargazers_url":"https://api.github.com/repos/ruiquelhas/houdin/stargazers","contributors_url":"https://api.github.com/repos/ruiquelhas/houdin/contributors","subscribers_url":"https://api.github.com/repos/ruiquelhas/houdin/subscribers","subscription_url":"https://api.github.com/repos/ruiquelhas/houdin/subscription","commits_url":"https://api.github.com/repos/ruiquelhas/houdin/commits{/sha}","git_commits_url":"https://api.github.com/repos/ruiquelhas/houdin/git/commits{/sha}","comments_url":"https://api.github.com/repos/ruiquelhas/houdin/comments{/number}","issue_comment_url":"https://api.github.com/repos/ruiquelhas/houdin/issues/comments{/number}","contents_url":"https://api.github.com/repos/ruiquelhas/houdin/contents/{+path}","compare_url":"https://api.github.com/repos/ruiquelhas/houdin/compare/{base}...{head}","merges_url":"https://api.github.com/repos/ruiquelhas/houdin/merges","archive_url":"https://api.github.com/repos/ruiquelhas/houdin/{archive_format}{/ref}","downloads_url":"https://api.github.com/repos/ruiquelhas/houdin/downloads","issues_url":"https://api.github.com/repos/ruiquelhas/houdin/issues{/number}","pulls_url":"https://api.github.com/repos/ruiquelhas/houdin/pulls{/number}","milestones_url":"https://api.github.com/repos/ruiquelhas/houdin/milestones{/number}","notifications_url":"https://api.github.com/repos/ruiquelhas/houdin/notifications{?since,all,participating}","labels_url":"https://api.github.com/repos/ruiquelhas/houdin/labels{/name}","releases_url":"https://api.github.com/repos/ruiquelhas/houdin/releases{/id}","deployments_url":"https://api.github.com/repos/ruiquelhas/houdin/deployments","created_at":"2015-11-15T17:40:18Z","updated_at":"2016-01-16T19:18:25Z","pushed_at":"2016-07-05T20:43:46Z","git_url":"git://github.com/ruiquelhas/houdin.git","ssh_url":"git@github.com:ruiquelhas/houdin.git","clone_url":"https://github.com/ruiquelhas/houdin.git","svn_url":"https://github.com/ruiquelhas/houdin","homepage":"https://www.npmjs.com/package/houdin","size":39,"stargazers_count":0,"watchers_count":0,"language":"JavaScript","has_issues":true,"has_downloads":true,"has_wiki":true,"has_pages":false,"forks_count":0,"mirror_url":null,"open_issues_count":0,"forks":0,"open_issues":0,"watchers":0,"default_branch":"master","permissions":{"admin":false,"push":false,"pull":true},"network_count":0,"subscribers_count":1}