{"id":30414485,"name":"builder","full_name":"closeheat/builder","owner":{"login":"closeheat","id":10816791,"avatar_url":"https://avatars.githubusercontent.com/u/10816791?v=3","gravatar_id":"","url":"https://api.github.com/users/closeheat","html_url":"https://github.com/closeheat","followers_url":"https://api.github.com/users/closeheat/followers","following_url":"https://api.github.com/users/closeheat/following{/other_user}","gists_url":"https://api.github.com/users/closeheat/gists{/gist_id}","starred_url":"https://api.github.com/users/closeheat/starred{/owner}{/repo}","subscriptions_url":"https://api.github.com/users/closeheat/subscriptions","organizations_url":"https://api.github.com/users/closeheat/orgs","repos_url":"https://api.github.com/users/closeheat/repos","events_url":"https://api.github.com/users/closeheat/events{/privacy}","received_events_url":"https://api.github.com/users/closeheat/received_events","type":"Organization","site_admin":false},"private":false,"html_url":"https://github.com/closeheat/builder","description":"Builds awesome apps","fork":false,"url":"https://api.github.com/repos/closeheat/builder","forks_url":"https://api.github.com/repos/closeheat/builder/forks","keys_url":"https://api.github.com/repos/closeheat/builder/keys{/key_id}","collaborators_url":"https://api.github.com/repos/closeheat/builder/collaborators{/collaborator}","teams_url":"https://api.github.com/repos/closeheat/builder/teams","hooks_url":"https://api.github.com/repos/closeheat/builder/hooks","issue_events_url":"https://api.github.com/repos/closeheat/builder/issues/events{/number}","events_url":"https://api.github.com/repos/closeheat/builder/events","assignees_url":"https://api.github.com/repos/closeheat/builder/assignees{/user}","branches_url":"https://api.github.com/repos/closeheat/builder/branches{/branch}","tags_url":"https://api.github.com/repos/closeheat/builder/tags","blobs_url":"https://api.github.com/repos/closeheat/builder/git/blobs{/sha}","git_tags_url":"https://api.github.com/repos/closeheat/builder/git/tags{/sha}","git_refs_url":"https://api.github.com/repos/closeheat/builder/git/refs{/sha}","trees_url":"https://api.github.com/repos/closeheat/builder/git/trees{/sha}","statuses_url":"https://api.github.com/repos/closeheat/builder/statuses/{sha}","languages_url":"https://api.github.com/repos/closeheat/builder/languages","stargazers_url":"https://api.github.com/repos/closeheat/builder/stargazers","contributors_url":"https://api.github.com/repos/closeheat/builder/contributors","subscribers_url":"https://api.github.com/repos/closeheat/builder/subscribers","subscription_url":"https://api.github.com/repos/closeheat/builder/subscription","commits_url":"https://api.github.com/repos/closeheat/builder/commits{/sha}","git_commits_url":"https://api.github.com/repos/closeheat/builder/git/commits{/sha}","comments_url":"https://api.github.com/repos/closeheat/builder/comments{/number}","issue_comment_url":"https://api.github.com/repos/closeheat/builder/issues/comments{/number}","contents_url":"https://api.github.com/repos/closeheat/builder/contents/{+path}","compare_url":"https://api.github.com/repos/closeheat/builder/compare/{base}...{head}","merges_url":"https://api.github.com/repos/closeheat/builder/merges","archive_url":"https://api.github.com/repos/closeheat/builder/{archive_format}{/ref}","downloads_url":"https://api.github.com/repos/closeheat/builder/downloads","issues_url":"https://api.github.com/repos/closeheat/builder/issues{/number}","pulls_url":"https://api.github.com/repos/closeheat/builder/pulls{/number}","milestones_url":"https://api.github.com/repos/closeheat/builder/milestones{/number}","notifications_url":"https://api.github.com/repos/closeheat/builder/notifications{?since,all,participating}","labels_url":"https://api.github.com/repos/closeheat/builder/labels{/name}","releases_url":"https://api.github.com/repos/closeheat/builder/releases{/id}","deployments_url":"https://api.github.com/repos/closeheat/builder/deployments","created_at":"2015-02-06T13:55:42Z","updated_at":"2016-04-01T09:35:28Z","pushed_at":"2016-02-07T11:40:04Z","git_url":"git://github.com/closeheat/builder.git","ssh_url":"git@github.com:closeheat/builder.git","clone_url":"https://github.com/closeheat/builder.git","svn_url":"https://github.com/closeheat/builder","homepage":"http://closeheat.com","size":4848,"stargazers_count":4,"watchers_count":4,"language":"JavaScript","has_issues":true,"has_downloads":true,"has_wiki":true,"has_pages":false,"forks_count":2,"mirror_url":null,"open_issues_count":1,"forks":2,"open_issues":1,"watchers":4,"default_branch":"master","permissions":{"admin":false,"push":false,"pull":true},"organization":{"login":"closeheat","id":10816791,"avatar_url":"https://avatars.githubusercontent.com/u/10816791?v=3","gravatar_id":"","url":"https://api.github.com/users/closeheat","html_url":"https://github.com/closeheat","followers_url":"https://api.github.com/users/closeheat/followers","following_url":"https://api.github.com/users/closeheat/following{/other_user}","gists_url":"https://api.github.com/users/closeheat/gists{/gist_id}","starred_url":"https://api.github.com/users/closeheat/starred{/owner}{/repo}","subscriptions_url":"https://api.github.com/users/closeheat/subscriptions","organizations_url":"https://api.github.com/users/closeheat/orgs","repos_url":"https://api.github.com/users/closeheat/repos","events_url":"https://api.github.com/users/closeheat/events{/privacy}","received_events_url":"https://api.github.com/users/closeheat/received_events","type":"Organization","site_admin":false},"network_count":2,"subscribers_count":3}