{"id":58395335,"name":"skynet","full_name":"benjifc/skynet","owner":{"login":"benjifc","id":2820756,"avatar_url":"https://avatars.githubusercontent.com/u/2820756?v=3","gravatar_id":"","url":"https://api.github.com/users/benjifc","html_url":"https://github.com/benjifc","followers_url":"https://api.github.com/users/benjifc/followers","following_url":"https://api.github.com/users/benjifc/following{/other_user}","gists_url":"https://api.github.com/users/benjifc/gists{/gist_id}","starred_url":"https://api.github.com/users/benjifc/starred{/owner}{/repo}","subscriptions_url":"https://api.github.com/users/benjifc/subscriptions","organizations_url":"https://api.github.com/users/benjifc/orgs","repos_url":"https://api.github.com/users/benjifc/repos","events_url":"https://api.github.com/users/benjifc/events{/privacy}","received_events_url":"https://api.github.com/users/benjifc/received_events","type":"User","site_admin":false},"private":false,"html_url":"https://github.com/benjifc/skynet","description":"telegram, nodejs, javascript, app, bot","fork":false,"url":"https://api.github.com/repos/benjifc/skynet","forks_url":"https://api.github.com/repos/benjifc/skynet/forks","keys_url":"https://api.github.com/repos/benjifc/skynet/keys{/key_id}","collaborators_url":"https://api.github.com/repos/benjifc/skynet/collaborators{/collaborator}","teams_url":"https://api.github.com/repos/benjifc/skynet/teams","hooks_url":"https://api.github.com/repos/benjifc/skynet/hooks","issue_events_url":"https://api.github.com/repos/benjifc/skynet/issues/events{/number}","events_url":"https://api.github.com/repos/benjifc/skynet/events","assignees_url":"https://api.github.com/repos/benjifc/skynet/assignees{/user}","branches_url":"https://api.github.com/repos/benjifc/skynet/branches{/branch}","tags_url":"https://api.github.com/repos/benjifc/skynet/tags","blobs_url":"https://api.github.com/repos/benjifc/skynet/git/blobs{/sha}","git_tags_url":"https://api.github.com/repos/benjifc/skynet/git/tags{/sha}","git_refs_url":"https://api.github.com/repos/benjifc/skynet/git/refs{/sha}","trees_url":"https://api.github.com/repos/benjifc/skynet/git/trees{/sha}","statuses_url":"https://api.github.com/repos/benjifc/skynet/statuses/{sha}","languages_url":"https://api.github.com/repos/benjifc/skynet/languages","stargazers_url":"https://api.github.com/repos/benjifc/skynet/stargazers","contributors_url":"https://api.github.com/repos/benjifc/skynet/contributors","subscribers_url":"https://api.github.com/repos/benjifc/skynet/subscribers","subscription_url":"https://api.github.com/repos/benjifc/skynet/subscription","commits_url":"https://api.github.com/repos/benjifc/skynet/commits{/sha}","git_commits_url":"https://api.github.com/repos/benjifc/skynet/git/commits{/sha}","comments_url":"https://api.github.com/repos/benjifc/skynet/comments{/number}","issue_comment_url":"https://api.github.com/repos/benjifc/skynet/issues/comments{/number}","contents_url":"https://api.github.com/repos/benjifc/skynet/contents/{+path}","compare_url":"https://api.github.com/repos/benjifc/skynet/compare/{base}...{head}","merges_url":"https://api.github.com/repos/benjifc/skynet/merges","archive_url":"https://api.github.com/repos/benjifc/skynet/{archive_format}{/ref}","downloads_url":"https://api.github.com/repos/benjifc/skynet/downloads","issues_url":"https://api.github.com/repos/benjifc/skynet/issues{/number}","pulls_url":"https://api.github.com/repos/benjifc/skynet/pulls{/number}","milestones_url":"https://api.github.com/repos/benjifc/skynet/milestones{/number}","notifications_url":"https://api.github.com/repos/benjifc/skynet/notifications{?since,all,participating}","labels_url":"https://api.github.com/repos/benjifc/skynet/labels{/name}","releases_url":"https://api.github.com/repos/benjifc/skynet/releases{/id}","deployments_url":"https://api.github.com/repos/benjifc/skynet/deployments","created_at":"2016-05-09T17:31:32Z","updated_at":"2016-05-09T17:57:56Z","pushed_at":"2016-05-10T09:10:23Z","git_url":"git://github.com/benjifc/skynet.git","ssh_url":"git@github.com:benjifc/skynet.git","clone_url":"https://github.com/benjifc/skynet.git","svn_url":"https://github.com/benjifc/skynet","homepage":null,"size":528,"stargazers_count":1,"watchers_count":1,"language":"JavaScript","has_issues":true,"has_downloads":true,"has_wiki":true,"has_pages":false,"forks_count":0,"mirror_url":null,"open_issues_count":0,"forks":0,"open_issues":0,"watchers":1,"default_branch":"master","permissions":{"admin":false,"push":false,"pull":true},"network_count":0,"subscribers_count":1}