{"id":58530427,"name":"fonsta","full_name":"roovenier/fonsta","owner":{"login":"roovenier","id":7780387,"avatar_url":"https://avatars.githubusercontent.com/u/7780387?v=3","gravatar_id":"","url":"https://api.github.com/users/roovenier","html_url":"https://github.com/roovenier","followers_url":"https://api.github.com/users/roovenier/followers","following_url":"https://api.github.com/users/roovenier/following{/other_user}","gists_url":"https://api.github.com/users/roovenier/gists{/gist_id}","starred_url":"https://api.github.com/users/roovenier/starred{/owner}{/repo}","subscriptions_url":"https://api.github.com/users/roovenier/subscriptions","organizations_url":"https://api.github.com/users/roovenier/orgs","repos_url":"https://api.github.com/users/roovenier/repos","events_url":"https://api.github.com/users/roovenier/events{/privacy}","received_events_url":"https://api.github.com/users/roovenier/received_events","type":"User","site_admin":false},"private":false,"html_url":"https://github.com/roovenier/fonsta","description":"Fonts package manager","fork":false,"url":"https://api.github.com/repos/roovenier/fonsta","forks_url":"https://api.github.com/repos/roovenier/fonsta/forks","keys_url":"https://api.github.com/repos/roovenier/fonsta/keys{/key_id}","collaborators_url":"https://api.github.com/repos/roovenier/fonsta/collaborators{/collaborator}","teams_url":"https://api.github.com/repos/roovenier/fonsta/teams","hooks_url":"https://api.github.com/repos/roovenier/fonsta/hooks","issue_events_url":"https://api.github.com/repos/roovenier/fonsta/issues/events{/number}","events_url":"https://api.github.com/repos/roovenier/fonsta/events","assignees_url":"https://api.github.com/repos/roovenier/fonsta/assignees{/user}","branches_url":"https://api.github.com/repos/roovenier/fonsta/branches{/branch}","tags_url":"https://api.github.com/repos/roovenier/fonsta/tags","blobs_url":"https://api.github.com/repos/roovenier/fonsta/git/blobs{/sha}","git_tags_url":"https://api.github.com/repos/roovenier/fonsta/git/tags{/sha}","git_refs_url":"https://api.github.com/repos/roovenier/fonsta/git/refs{/sha}","trees_url":"https://api.github.com/repos/roovenier/fonsta/git/trees{/sha}","statuses_url":"https://api.github.com/repos/roovenier/fonsta/statuses/{sha}","languages_url":"https://api.github.com/repos/roovenier/fonsta/languages","stargazers_url":"https://api.github.com/repos/roovenier/fonsta/stargazers","contributors_url":"https://api.github.com/repos/roovenier/fonsta/contributors","subscribers_url":"https://api.github.com/repos/roovenier/fonsta/subscribers","subscription_url":"https://api.github.com/repos/roovenier/fonsta/subscription","commits_url":"https://api.github.com/repos/roovenier/fonsta/commits{/sha}","git_commits_url":"https://api.github.com/repos/roovenier/fonsta/git/commits{/sha}","comments_url":"https://api.github.com/repos/roovenier/fonsta/comments{/number}","issue_comment_url":"https://api.github.com/repos/roovenier/fonsta/issues/comments{/number}","contents_url":"https://api.github.com/repos/roovenier/fonsta/contents/{+path}","compare_url":"https://api.github.com/repos/roovenier/fonsta/compare/{base}...{head}","merges_url":"https://api.github.com/repos/roovenier/fonsta/merges","archive_url":"https://api.github.com/repos/roovenier/fonsta/{archive_format}{/ref}","downloads_url":"https://api.github.com/repos/roovenier/fonsta/downloads","issues_url":"https://api.github.com/repos/roovenier/fonsta/issues{/number}","pulls_url":"https://api.github.com/repos/roovenier/fonsta/pulls{/number}","milestones_url":"https://api.github.com/repos/roovenier/fonsta/milestones{/number}","notifications_url":"https://api.github.com/repos/roovenier/fonsta/notifications{?since,all,participating}","labels_url":"https://api.github.com/repos/roovenier/fonsta/labels{/name}","releases_url":"https://api.github.com/repos/roovenier/fonsta/releases{/id}","deployments_url":"https://api.github.com/repos/roovenier/fonsta/deployments","created_at":"2016-05-11T09:11:17Z","updated_at":"2016-05-22T10:35:17Z","pushed_at":"2016-07-07T16:50:54Z","git_url":"git://github.com/roovenier/fonsta.git","ssh_url":"git@github.com:roovenier/fonsta.git","clone_url":"https://github.com/roovenier/fonsta.git","svn_url":"https://github.com/roovenier/fonsta","homepage":"","size":61,"stargazers_count":1,"watchers_count":1,"language":"JavaScript","has_issues":true,"has_downloads":true,"has_wiki":true,"has_pages":false,"forks_count":0,"mirror_url":null,"open_issues_count":0,"forks":0,"open_issues":0,"watchers":1,"default_branch":"master","permissions":{"admin":false,"push":false,"pull":true},"network_count":0,"subscribers_count":2}