{"id":11558117,"name":"mix-tool","full_name":"jiawulu/mix-tool","owner":{"login":"jiawulu","id":748188,"avatar_url":"https://avatars.githubusercontent.com/u/748188?v=3","gravatar_id":"","url":"https://api.github.com/users/jiawulu","html_url":"https://github.com/jiawulu","followers_url":"https://api.github.com/users/jiawulu/followers","following_url":"https://api.github.com/users/jiawulu/following{/other_user}","gists_url":"https://api.github.com/users/jiawulu/gists{/gist_id}","starred_url":"https://api.github.com/users/jiawulu/starred{/owner}{/repo}","subscriptions_url":"https://api.github.com/users/jiawulu/subscriptions","organizations_url":"https://api.github.com/users/jiawulu/orgs","repos_url":"https://api.github.com/users/jiawulu/repos","events_url":"https://api.github.com/users/jiawulu/events{/privacy}","received_events_url":"https://api.github.com/users/jiawulu/received_events","type":"User","site_admin":false},"private":false,"html_url":"https://github.com/jiawulu/mix-tool","description":"","fork":false,"url":"https://api.github.com/repos/jiawulu/mix-tool","forks_url":"https://api.github.com/repos/jiawulu/mix-tool/forks","keys_url":"https://api.github.com/repos/jiawulu/mix-tool/keys{/key_id}","collaborators_url":"https://api.github.com/repos/jiawulu/mix-tool/collaborators{/collaborator}","teams_url":"https://api.github.com/repos/jiawulu/mix-tool/teams","hooks_url":"https://api.github.com/repos/jiawulu/mix-tool/hooks","issue_events_url":"https://api.github.com/repos/jiawulu/mix-tool/issues/events{/number}","events_url":"https://api.github.com/repos/jiawulu/mix-tool/events","assignees_url":"https://api.github.com/repos/jiawulu/mix-tool/assignees{/user}","branches_url":"https://api.github.com/repos/jiawulu/mix-tool/branches{/branch}","tags_url":"https://api.github.com/repos/jiawulu/mix-tool/tags","blobs_url":"https://api.github.com/repos/jiawulu/mix-tool/git/blobs{/sha}","git_tags_url":"https://api.github.com/repos/jiawulu/mix-tool/git/tags{/sha}","git_refs_url":"https://api.github.com/repos/jiawulu/mix-tool/git/refs{/sha}","trees_url":"https://api.github.com/repos/jiawulu/mix-tool/git/trees{/sha}","statuses_url":"https://api.github.com/repos/jiawulu/mix-tool/statuses/{sha}","languages_url":"https://api.github.com/repos/jiawulu/mix-tool/languages","stargazers_url":"https://api.github.com/repos/jiawulu/mix-tool/stargazers","contributors_url":"https://api.github.com/repos/jiawulu/mix-tool/contributors","subscribers_url":"https://api.github.com/repos/jiawulu/mix-tool/subscribers","subscription_url":"https://api.github.com/repos/jiawulu/mix-tool/subscription","commits_url":"https://api.github.com/repos/jiawulu/mix-tool/commits{/sha}","git_commits_url":"https://api.github.com/repos/jiawulu/mix-tool/git/commits{/sha}","comments_url":"https://api.github.com/repos/jiawulu/mix-tool/comments{/number}","issue_comment_url":"https://api.github.com/repos/jiawulu/mix-tool/issues/comments{/number}","contents_url":"https://api.github.com/repos/jiawulu/mix-tool/contents/{+path}","compare_url":"https://api.github.com/repos/jiawulu/mix-tool/compare/{base}...{head}","merges_url":"https://api.github.com/repos/jiawulu/mix-tool/merges","archive_url":"https://api.github.com/repos/jiawulu/mix-tool/{archive_format}{/ref}","downloads_url":"https://api.github.com/repos/jiawulu/mix-tool/downloads","issues_url":"https://api.github.com/repos/jiawulu/mix-tool/issues{/number}","pulls_url":"https://api.github.com/repos/jiawulu/mix-tool/pulls{/number}","milestones_url":"https://api.github.com/repos/jiawulu/mix-tool/milestones{/number}","notifications_url":"https://api.github.com/repos/jiawulu/mix-tool/notifications{?since,all,participating}","labels_url":"https://api.github.com/repos/jiawulu/mix-tool/labels{/name}","releases_url":"https://api.github.com/repos/jiawulu/mix-tool/releases{/id}","deployments_url":"https://api.github.com/repos/jiawulu/mix-tool/deployments","created_at":"2013-07-21T06:35:26Z","updated_at":"2013-10-19T20:29:20Z","pushed_at":"2013-07-25T13:39:20Z","git_url":"git://github.com/jiawulu/mix-tool.git","ssh_url":"git@github.com:jiawulu/mix-tool.git","clone_url":"https://github.com/jiawulu/mix-tool.git","svn_url":"https://github.com/jiawulu/mix-tool","homepage":null,"size":128,"stargazers_count":0,"watchers_count":0,"language":"JavaScript","has_issues":true,"has_downloads":true,"has_wiki":true,"has_pages":false,"forks_count":0,"mirror_url":null,"open_issues_count":0,"forks":0,"open_issues":0,"watchers":0,"default_branch":"master","permissions":{"admin":false,"push":false,"pull":true},"network_count":0,"subscribers_count":1}