{"id":58516134,"name":"eslint-plugin-gm","full_name":"gmfe/eslint-plugin-gm","owner":{"login":"gmfe","id":14875414,"avatar_url":"https://avatars.githubusercontent.com/u/14875414?v=3","gravatar_id":"","url":"https://api.github.com/users/gmfe","html_url":"https://github.com/gmfe","followers_url":"https://api.github.com/users/gmfe/followers","following_url":"https://api.github.com/users/gmfe/following{/other_user}","gists_url":"https://api.github.com/users/gmfe/gists{/gist_id}","starred_url":"https://api.github.com/users/gmfe/starred{/owner}{/repo}","subscriptions_url":"https://api.github.com/users/gmfe/subscriptions","organizations_url":"https://api.github.com/users/gmfe/orgs","repos_url":"https://api.github.com/users/gmfe/repos","events_url":"https://api.github.com/users/gmfe/events{/privacy}","received_events_url":"https://api.github.com/users/gmfe/received_events","type":"Organization","site_admin":false},"private":false,"html_url":"https://github.com/gmfe/eslint-plugin-gm","description":"eslint配置规则","fork":false,"url":"https://api.github.com/repos/gmfe/eslint-plugin-gm","forks_url":"https://api.github.com/repos/gmfe/eslint-plugin-gm/forks","keys_url":"https://api.github.com/repos/gmfe/eslint-plugin-gm/keys{/key_id}","collaborators_url":"https://api.github.com/repos/gmfe/eslint-plugin-gm/collaborators{/collaborator}","teams_url":"https://api.github.com/repos/gmfe/eslint-plugin-gm/teams","hooks_url":"https://api.github.com/repos/gmfe/eslint-plugin-gm/hooks","issue_events_url":"https://api.github.com/repos/gmfe/eslint-plugin-gm/issues/events{/number}","events_url":"https://api.github.com/repos/gmfe/eslint-plugin-gm/events","assignees_url":"https://api.github.com/repos/gmfe/eslint-plugin-gm/assignees{/user}","branches_url":"https://api.github.com/repos/gmfe/eslint-plugin-gm/branches{/branch}","tags_url":"https://api.github.com/repos/gmfe/eslint-plugin-gm/tags","blobs_url":"https://api.github.com/repos/gmfe/eslint-plugin-gm/git/blobs{/sha}","git_tags_url":"https://api.github.com/repos/gmfe/eslint-plugin-gm/git/tags{/sha}","git_refs_url":"https://api.github.com/repos/gmfe/eslint-plugin-gm/git/refs{/sha}","trees_url":"https://api.github.com/repos/gmfe/eslint-plugin-gm/git/trees{/sha}","statuses_url":"https://api.github.com/repos/gmfe/eslint-plugin-gm/statuses/{sha}","languages_url":"https://api.github.com/repos/gmfe/eslint-plugin-gm/languages","stargazers_url":"https://api.github.com/repos/gmfe/eslint-plugin-gm/stargazers","contributors_url":"https://api.github.com/repos/gmfe/eslint-plugin-gm/contributors","subscribers_url":"https://api.github.com/repos/gmfe/eslint-plugin-gm/subscribers","subscription_url":"https://api.github.com/repos/gmfe/eslint-plugin-gm/subscription","commits_url":"https://api.github.com/repos/gmfe/eslint-plugin-gm/commits{/sha}","git_commits_url":"https://api.github.com/repos/gmfe/eslint-plugin-gm/git/commits{/sha}","comments_url":"https://api.github.com/repos/gmfe/eslint-plugin-gm/comments{/number}","issue_comment_url":"https://api.github.com/repos/gmfe/eslint-plugin-gm/issues/comments{/number}","contents_url":"https://api.github.com/repos/gmfe/eslint-plugin-gm/contents/{+path}","compare_url":"https://api.github.com/repos/gmfe/eslint-plugin-gm/compare/{base}...{head}","merges_url":"https://api.github.com/repos/gmfe/eslint-plugin-gm/merges","archive_url":"https://api.github.com/repos/gmfe/eslint-plugin-gm/{archive_format}{/ref}","downloads_url":"https://api.github.com/repos/gmfe/eslint-plugin-gm/downloads","issues_url":"https://api.github.com/repos/gmfe/eslint-plugin-gm/issues{/number}","pulls_url":"https://api.github.com/repos/gmfe/eslint-plugin-gm/pulls{/number}","milestones_url":"https://api.github.com/repos/gmfe/eslint-plugin-gm/milestones{/number}","notifications_url":"https://api.github.com/repos/gmfe/eslint-plugin-gm/notifications{?since,all,participating}","labels_url":"https://api.github.com/repos/gmfe/eslint-plugin-gm/labels{/name}","releases_url":"https://api.github.com/repos/gmfe/eslint-plugin-gm/releases{/id}","deployments_url":"https://api.github.com/repos/gmfe/eslint-plugin-gm/deployments","created_at":"2016-05-11T05:16:12Z","updated_at":"2016-05-26T02:42:59Z","pushed_at":"2016-05-11T08:58:32Z","git_url":"git://github.com/gmfe/eslint-plugin-gm.git","ssh_url":"git@github.com:gmfe/eslint-plugin-gm.git","clone_url":"https://github.com/gmfe/eslint-plugin-gm.git","svn_url":"https://github.com/gmfe/eslint-plugin-gm","homepage":null,"size":2,"stargazers_count":2,"watchers_count":2,"language":"JavaScript","has_issues":true,"has_downloads":true,"has_wiki":true,"has_pages":false,"forks_count":1,"mirror_url":null,"open_issues_count":0,"forks":1,"open_issues":0,"watchers":2,"default_branch":"master","permissions":{"admin":false,"push":false,"pull":true},"organization":{"login":"gmfe","id":14875414,"avatar_url":"https://avatars.githubusercontent.com/u/14875414?v=3","gravatar_id":"","url":"https://api.github.com/users/gmfe","html_url":"https://github.com/gmfe","followers_url":"https://api.github.com/users/gmfe/followers","following_url":"https://api.github.com/users/gmfe/following{/other_user}","gists_url":"https://api.github.com/users/gmfe/gists{/gist_id}","starred_url":"https://api.github.com/users/gmfe/starred{/owner}{/repo}","subscriptions_url":"https://api.github.com/users/gmfe/subscriptions","organizations_url":"https://api.github.com/users/gmfe/orgs","repos_url":"https://api.github.com/users/gmfe/repos","events_url":"https://api.github.com/users/gmfe/events{/privacy}","received_events_url":"https://api.github.com/users/gmfe/received_events","type":"Organization","site_admin":false},"network_count":1,"subscribers_count":2}