{"id":41540851,"name":"learnyoupython","full_name":"Gtskk/learnyoupython","owner":{"login":"Gtskk","id":2942038,"avatar_url":"https://avatars.githubusercontent.com/u/2942038?v=3","gravatar_id":"","url":"https://api.github.com/users/Gtskk","html_url":"https://github.com/Gtskk","followers_url":"https://api.github.com/users/Gtskk/followers","following_url":"https://api.github.com/users/Gtskk/following{/other_user}","gists_url":"https://api.github.com/users/Gtskk/gists{/gist_id}","starred_url":"https://api.github.com/users/Gtskk/starred{/owner}{/repo}","subscriptions_url":"https://api.github.com/users/Gtskk/subscriptions","organizations_url":"https://api.github.com/users/Gtskk/orgs","repos_url":"https://api.github.com/users/Gtskk/repos","events_url":"https://api.github.com/users/Gtskk/events{/privacy}","received_events_url":"https://api.github.com/users/Gtskk/received_events","type":"User","site_admin":false},"private":false,"html_url":"https://github.com/Gtskk/learnyoupython","description":"学习Python的好工具","fork":false,"url":"https://api.github.com/repos/Gtskk/learnyoupython","forks_url":"https://api.github.com/repos/Gtskk/learnyoupython/forks","keys_url":"https://api.github.com/repos/Gtskk/learnyoupython/keys{/key_id}","collaborators_url":"https://api.github.com/repos/Gtskk/learnyoupython/collaborators{/collaborator}","teams_url":"https://api.github.com/repos/Gtskk/learnyoupython/teams","hooks_url":"https://api.github.com/repos/Gtskk/learnyoupython/hooks","issue_events_url":"https://api.github.com/repos/Gtskk/learnyoupython/issues/events{/number}","events_url":"https://api.github.com/repos/Gtskk/learnyoupython/events","assignees_url":"https://api.github.com/repos/Gtskk/learnyoupython/assignees{/user}","branches_url":"https://api.github.com/repos/Gtskk/learnyoupython/branches{/branch}","tags_url":"https://api.github.com/repos/Gtskk/learnyoupython/tags","blobs_url":"https://api.github.com/repos/Gtskk/learnyoupython/git/blobs{/sha}","git_tags_url":"https://api.github.com/repos/Gtskk/learnyoupython/git/tags{/sha}","git_refs_url":"https://api.github.com/repos/Gtskk/learnyoupython/git/refs{/sha}","trees_url":"https://api.github.com/repos/Gtskk/learnyoupython/git/trees{/sha}","statuses_url":"https://api.github.com/repos/Gtskk/learnyoupython/statuses/{sha}","languages_url":"https://api.github.com/repos/Gtskk/learnyoupython/languages","stargazers_url":"https://api.github.com/repos/Gtskk/learnyoupython/stargazers","contributors_url":"https://api.github.com/repos/Gtskk/learnyoupython/contributors","subscribers_url":"https://api.github.com/repos/Gtskk/learnyoupython/subscribers","subscription_url":"https://api.github.com/repos/Gtskk/learnyoupython/subscription","commits_url":"https://api.github.com/repos/Gtskk/learnyoupython/commits{/sha}","git_commits_url":"https://api.github.com/repos/Gtskk/learnyoupython/git/commits{/sha}","comments_url":"https://api.github.com/repos/Gtskk/learnyoupython/comments{/number}","issue_comment_url":"https://api.github.com/repos/Gtskk/learnyoupython/issues/comments{/number}","contents_url":"https://api.github.com/repos/Gtskk/learnyoupython/contents/{+path}","compare_url":"https://api.github.com/repos/Gtskk/learnyoupython/compare/{base}...{head}","merges_url":"https://api.github.com/repos/Gtskk/learnyoupython/merges","archive_url":"https://api.github.com/repos/Gtskk/learnyoupython/{archive_format}{/ref}","downloads_url":"https://api.github.com/repos/Gtskk/learnyoupython/downloads","issues_url":"https://api.github.com/repos/Gtskk/learnyoupython/issues{/number}","pulls_url":"https://api.github.com/repos/Gtskk/learnyoupython/pulls{/number}","milestones_url":"https://api.github.com/repos/Gtskk/learnyoupython/milestones{/number}","notifications_url":"https://api.github.com/repos/Gtskk/learnyoupython/notifications{?since,all,participating}","labels_url":"https://api.github.com/repos/Gtskk/learnyoupython/labels{/name}","releases_url":"https://api.github.com/repos/Gtskk/learnyoupython/releases{/id}","deployments_url":"https://api.github.com/repos/Gtskk/learnyoupython/deployments","created_at":"2015-08-28T10:11:40Z","updated_at":"2015-09-08T03:22:48Z","pushed_at":"2015-09-08T02:47:58Z","git_url":"git://github.com/Gtskk/learnyoupython.git","ssh_url":"git@github.com:Gtskk/learnyoupython.git","clone_url":"https://github.com/Gtskk/learnyoupython.git","svn_url":"https://github.com/Gtskk/learnyoupython","homepage":null,"size":1656,"stargazers_count":4,"watchers_count":4,"language":"HTML","has_issues":true,"has_downloads":true,"has_wiki":true,"has_pages":false,"forks_count":0,"mirror_url":null,"open_issues_count":0,"forks":0,"open_issues":0,"watchers":4,"default_branch":"master","permissions":{"admin":false,"push":false,"pull":true},"network_count":0,"subscribers_count":2}